vigil/__init__.py
vigil/__main__.py
vigil/api.py
vigil/cli.py
vigil/cards/__init__.py
vigil/cards/linter.py
vigil/cards/schemas.py
vigil/cards/templates/dataset_card.md
vigil/cards/templates/experiment_card.md
vigil/cli/__init__.py
vigil/cli/__main__.py
vigil/core/__init__.py
vigil/core/env.py
vigil/core/pipeline.py
vigil/core/policy.py
vigil/core/receipts.py
vigil/core/signer.py
vigil/examples/genomics-starter/LICENSE
vigil/examples/genomics-starter/LICENSE-ORL
vigil/examples/genomics-starter/README.md
vigil/examples/genomics-starter/pyproject.toml
vigil/examples/genomics-starter/vigil.yaml
vigil/examples/genomics-starter/app/__init__.py
vigil/examples/genomics-starter/app/code/__init__.py
vigil/examples/genomics-starter/app/code/configs/params/default.yaml
vigil/examples/genomics-starter/app/code/configs/profiles/README_CLOUD.md
vigil/examples/genomics-starter/app/code/configs/profiles/README_HPC.md
vigil/examples/genomics-starter/app/code/configs/profiles/cpu.yaml
vigil/examples/genomics-starter/app/code/configs/profiles/pbs.yaml
vigil/examples/genomics-starter/app/code/configs/profiles/sge.yaml
vigil/examples/genomics-starter/app/code/configs/profiles/slurm.yaml
vigil/examples/genomics-starter/app/code/configs/profiles/slurm_cluster.yaml
vigil/examples/genomics-starter/app/code/configs/profiles/slurm_status.py
vigil/examples/genomics-starter/app/code/lib/README_DATABASES.md
vigil/examples/genomics-starter/app/code/lib/__init__.py
vigil/examples/genomics-starter/app/code/lib/genomics_databases.py
vigil/examples/genomics-starter/app/code/lib/genomics_metrics.py
vigil/examples/genomics-starter/app/code/lib/steps/__init__.py
vigil/examples/genomics-starter/app/code/lib/steps/annotate.py
vigil/examples/genomics-starter/app/code/lib/steps/filter.py
vigil/examples/genomics-starter/app/code/lib/steps/metrics.py
vigil/examples/genomics-starter/app/code/pipelines/Snakefile
vigil/examples/genomics-starter/app/code/tools/sciencecast.py
vigil_core-0.3.10.dist-info/METADATA
vigil_core-0.3.10.dist-info/WHEEL
vigil_core-0.3.10.dist-info/entry_points.txt
vigil_core-0.3.10.dist-info/RECORD
