Metadata-Version: 2.4
Name: vigil-core
Version: 0.3.10
Summary: Vigil Core: Cryptographic kernel for reproducible science
Author: Science Abundance
License: Apache-2.0
Keywords: cryptography,pipeline,provenance,receipts,reproducible,science
Classifier: Development Status :: 3 - Alpha
Classifier: Intended Audience :: Science/Research
Classifier: License :: OSI Approved :: Apache Software License
Classifier: Programming Language :: Python :: 3
Classifier: Programming Language :: Python :: 3.11
Classifier: Programming Language :: Python :: 3.12
Classifier: Programming Language :: Python :: 3.13
Requires-Python: >=3.11
Requires-Dist: cryptography>=41.0.0
Requires-Dist: pydantic>=2.0.0
Requires-Dist: pyyaml>=6.0.0
Requires-Dist: rich>=14.0.0
Requires-Dist: snakemake>=8.0.0
Requires-Dist: typer>=0.19.0
Provides-Extra: dev
Requires-Dist: mypy>=1.8.0; extra == 'dev'
Requires-Dist: pytest>=8.3.0; extra == 'dev'
Requires-Dist: ruff>=0.1.0; extra == 'dev'
Provides-Extra: platform
Requires-Dist: vigil-client; extra == 'platform'
